CaseLawSscraper/CaseHeaderScraper.py
CaseLawSscraper/CaseInfoScraper.py
CaseLawSscraper/FullTextScraper.py
CaseLawSscraper/Save_to_json.py
CaseLawSscraper/__init__.py
tests/__init__.py
tests/test_module1.py
tests/test_module2.py
tests/test_module3.py
CaseLawSscraper-0.1.dist-info/LICENSE
CaseLawSscraper-0.1.dist-info/METADATA
CaseLawSscraper-0.1.dist-info/WHEEL
CaseLawSscraper-0.1.dist-info/top_level.txt
CaseLawSscraper-0.1.dist-info/RECORD
